nercone_fastget/__init__.py
nercone_fastget/__main__.py
nercone_fastget/fastget.py
nercone_fastget-6.4.0.dist-info/WHEEL
nercone_fastget-6.4.0.dist-info/entry_points.txt
nercone_fastget-6.4.0.dist-info/METADATA
nercone_fastget-6.4.0.dist-info/RECORD
