Metadata-Version: 2.3
Name: nercone-fastget
Version: 6.4.0
Summary: High-speed File Downloading Tool
Author: Nercone
Author-email: Nercone <nercone@diamondgotcat.net>
License: MIT
Classifier: Programming Language :: Python :: 3
Classifier: License :: OSI Approved :: MIT License
Classifier: Operating System :: OS Independent
Requires-Dist: rich
Requires-Dist: httpx[http2]
Requires-Python: >=3.8
